gamedatacrunch/__init__.py
gamedatacrunch/compatibility.py
gamedatacrunch/download.py
gamedatacrunch/load.py
gamedatacrunch/utils.py
gamedatacrunch/tests/__init__.py
gamedatacrunch/tests/test_compatibility.py
gamedatacrunch/tests/test_download.py
gamedatacrunch/tests/test_load.py
gamedatacrunch/tests/test_utils.py
gamedatacrunch-0.0.3.dist-info/LICENSE
gamedatacrunch-0.0.3.dist-info/METADATA
gamedatacrunch-0.0.3.dist-info/WHEEL
gamedatacrunch-0.0.3.dist-info/top_level.txt
gamedatacrunch-0.0.3.dist-info/RECORD
