Metadata-Version: 2.1
Name: gamedatacrunch
Version: 0.0.3
Summary: GameDataCrunch API on PyPI
Home-page: https://github.com/woctezuma/gamedatacrunch
Author: Wok
Author-email: wok@tuta.io
License: UNKNOWN
Download-URL: https://github.com/woctezuma/gamedatacrunch/archive/0.0.3.tar.gz
Keywords: steam,gamedatacrunch,api
Platform: UNKNOWN
Classifier: Development Status :: 2 - Pre-Alpha
Classifier: Topic :: Games/Entertainment
Classifier: Programming Language :: Python :: 3
Classifier: License :: OSI Approved :: MIT License
Classifier: Operating System :: OS Independent
Requires-Python: >=3
Requires-Dist: requests
